setup.cfg
setup.py
DynDNSLogClient/DynDNSLogClient.py
DynDNSLogClient/__init__.py
DynDNSLogClient.egg-info/PKG-INFO
DynDNSLogClient.egg-info/SOURCES.txt
DynDNSLogClient.egg-info/dependency_links.txt
DynDNSLogClient.egg-info/requires.txt
DynDNSLogClient.egg-info/top_level.txt
DynDNSLogClient/DynDNSClient/Configuration.py
DynDNSLogClient/DynDNSClient/DynClientLogger.py
DynDNSLogClient/DynDNSClient/FileWriter.py
DynDNSLogClient/DynDNSClient/Metrics.py
DynDNSLogClient/DynDNSClient/__init__.py