Metadata-Version: 1.1
Name: DynDNSLogClient
Version: 0.0.17
Summary: Dyn client for receiving DNS query log data from the cloud
Home-page: https://github.com/rabinnh/Dyn
Author: Richard Bross
Author-email: rbross1956@gmail.com
License: UNKNOWN
Download-URL: https://github.com/rabinnh/Dyn/tarball/0.0.17
Keywords: DNS,Dyn,Logs
Platform: UNKNOWN
